{
  "mvrvZ": 1.2,
  "mvrvZDate": "2026-06-11",
  "nupl": 0.166,
  "nuplDate": "2026-06-11",
  "sopr": 0.9885,
  "soprDate": "2026-06-11",
  "funding": 0.00003,
  "fundingDate": "2026-06-11 18:00:00",
  "puell": 0.633,
  "utxo1m": 3.5,
  "utxo7yr": 26.1,
  "lthSopr": 0.6806,
  "sthSopr": 0.9949,
  "reserveRisk": 0.000517,
  "etfFlow": -3766.6,
  "etfFlowDate": "2026-06-10",
  "updatedAt": "2026-06-12T23:56:52.772Z",
  "updatedAtKST": "2026. 6. 13. AM 8:56:52",
  "source": "bitcoin-data.com (BGeometrics)",
  "utxo1mDate": "2026-06-11",
  "utxo7yrDate": "2026-06-11",
  "puellDate": "2026-06-11",
  "lthSoprDate": "2026-06-11",
  "sthSoprDate": "2026-06-11",
  "reserveRiskDate": "2026-06-11"
}