{
  "mvrvZ": 1.21,
  "mvrvZDate": "2026-07-11",
  "nupl": 0.176,
  "nuplDate": "2026-07-11",
  "sopr": 1.0007,
  "soprDate": "2026-07-11",
  "funding": 0.00004,
  "fundingDate": "2026-07-11 18:00:00",
  "puell": 0.693,
  "utxo1m": 3.3,
  "utxo7yr": 26.2,
  "lthSopr": 0.9295,
  "sthSopr": 1.001,
  "reserveRisk": 0.000511,
  "etfFlow": -1543,
  "etfFlowDate": "2026-07-09",
  "updatedAt": "2026-07-13T12:17:14.949Z",
  "updatedAtKST": "2026. 7. 13. PM 9:17:14",
  "source": "bitcoin-data.com (BGeometrics)",
  "utxo1mDate": "2026-07-12",
  "utxo7yrDate": "2026-07-12",
  "puellDate": "2026-07-11",
  "lthSoprDate": "2026-07-11",
  "sthSoprDate": "2026-07-11",
  "reserveRiskDate": "2026-07-11"
}